lab4/mux_8_1_logic.v
module mux_8_1_logic (
    input [3:0] i0, i1, i2, i3, i4, i5, i6, i7, 
    input [2:0] s,                             
    output [3:0] y 
);                           

    assign y[3] = (i0[3] & ~s[0] & ~s[1] & ~s[2]) |
                  (i1[3] &  s[0] & ~s[1] & ~s[2]) |
                  (i2[3] & ~s[0] &  s[1] & ~s[2]) |
                  (i3[3] &  s[0] &  s[1] & ~s[2]) |
                  (i4[3] & ~s[0] & ~s[1] &  s[2]) |
                  (i5[3] &  s[0] & ~s[1] &  s[2]) |
                  (i6[3] & ~s[0] &  s[1] &  s[2]) |
                  (i7[3] &  s[0] &  s[1] &  s[2]);

    assign y[2] = (i0[2] & ~s[0] & ~s[1] & ~s[2]) |
                  (i1[2] &  s[0] & ~s[1] & ~s[2]) |
                  (i2[2] & ~s[0] &  s[1] & ~s[2]) |
                  (i3[2] &  s[0] &  s[1] & ~s[2]) |
                  (i4[2] & ~s[0] & ~s[1] &  s[2]) |
                  (i5[2] &  s[0] & ~s[1] &  s[2]) |
                  (i6[2] & ~s[0] &  s[1] &  s[2]) |
                  (i7[2] &  s[0] &  s[1] &  s[2]);

    assign y[1] = (i0[1] & ~s[0] & ~s[1] & ~s[2]) |
                  (i1[1] &  s[0] & ~s[1] & ~s[2]) |
                  (i2[1] & ~s[0] &  s[1] & ~s[2]) |
                  (i3[1] &  s[0] &  s[1] & ~s[2]) |
                  (i4[1] & ~s[0] & ~s[1] &  s[2]) |
                  (i5[1] &  s[0] & ~s[1] &  s[2]) |
                  (i6[1] & ~s[0] &  s[1] &  s[2]) |
                  (i7[1] &  s[0] &  s[1] &  s[2]);

    assign y[0] = (i0[0] & ~s[0] & ~s[1] & ~s[2]) |
                  (i1[0] &  s[0] & ~s[1] & ~s[2]) |
                  (i2[0] & ~s[0] &  s[1] & ~s[2]) |
                  (i3[0] &  s[0] &  s[1] & ~s[2]) |
                  (i4[0] & ~s[0] & ~s[1] &  s[2]) |
                  (i5[0] &  s[0] & ~s[1] &  s[2]) |
                  (i6[0] & ~s[0] &  s[1] &  s[2]) |
                  (i7[0] &  s[0] &  s[1] &  s[2]);

endmodule

lab4/alu.v
`include "mux_8_1_logic.v"

module alu (
    input [3:0] src_a,
    input [3:0] src_b,
    input [2:0] operation,
    output [3:0] alu_result,
    output zero_flag
);

    wire [3:0] w0, w1, w2, w3, w4, w5, w6, w7;

    assign w0 = src_a & src_b;
    assign w1 = src_a | src_b;
    assign w2 = src_a + src_b;
    assign w3 = src_a << 1;
    assign w4 = src_a - src_b;
    assign w5 = src_a >> 1;
    assign w6 = (src_a < src_b) ? 4'b0001 : 4'b0000;
    assign w7 = src_a ^ src_b;

    mux_8_1_logic mux (
        .i0(w0),
        .i1(w1),
        .i2(w2),
        .i3(w3),
        .i4(w4),
        .i5(w5),
        .i6(w6),
        .i7(w7),
        .s(operation),
        .y(alu_result)
    );

    assign zero_flag = (alu_result == 4'b0000);

endmodule

lab4/alu_tb.v
`include "alu.v"

module alu_tb ();

    parameter DATA_WIDTH = 4;
    parameter OPCODE_LENGTH = 3;

    reg [DATA_WIDTH - 1:0] A;
    reg [DATA_WIDTH - 1:0] B;
    reg [OPCODE_LENGTH - 1:0] OP;

    wire [DATA_WIDTH - 1:0] RESULT;
    wire F_ZERO;

    alu uut (
        .src_a(A),
        .src_b(B),
        .operation(OP),
        .alu_result(RESULT),
        .zero_flag(F_ZERO)
    );

    initial
        begin
            A = 1; B = 2; OP = 3'b000;
            #1 A = 2; B = 3; OP = 3'b001;
            #1 A = 1; B = 3; OP = 3'b010;
            #1 A = 2; B = 1; OP = 3'b011;
            #1 A = 4; B = 1; OP = 3'b100;
            #1 A = 4; B = 1; OP = 3'b101;
            #1 A = 6; B = 2; OP = 3'b110;
            #1 A = 3; B = 2; OP = 3'b111;
        end

    initial begin
        $monitor($time, " A = %d, B = %d, OP = %b, RESULT = %b, Z_FLAG = %b", 
                 A, B, OP, RESULT, F_ZERO);
        #20 $finish;
    end

    initial
        begin
            $dumpfile("alu_tb.vcd");
            $dumpvars(0, alu_tb);
        end

endmodule

lab4/alu_tb.vcd
$date
	Thu Nov  7 06:28:54 2024
$end
$version
	Icarus Verilog
$end
$timescale
	1s
$end
$scope module alu_tb $end
$var wire 4 ! RESULT [3:0] $end
$var wire 1 " F_ZERO $end
$var parameter 32 # DATA_WIDTH $end
$var parameter 32 $ OPCODE_LENGTH $end
$var reg 4 % A [3:0] $end
$var reg 4 & B [3:0] $end
$var reg 3 ' OP [2:0] $end
$scope module uut $end
$var wire 3 ( operation [2:0] $end
$var wire 4 ) src_a [3:0] $end
$var wire 4 * src_b [3:0] $end
$var wire 4 + w0 [3:0] $end
$var wire 4 , w1 [3:0] $end
$var wire 4 - w7 [3:0] $end
$var wire 1 " zero_flag $end
$var wire 4 . w6 [3:0] $end
$var wire 4 / w5 [3:0] $end
$var wire 4 0 w4 [3:0] $end
$var wire 4 1 w3 [3:0] $end
$var wire 4 2 w2 [3:0] $end
$var wire 4 3 alu_result [3:0] $end
$scope module mux $end
$var wire 4 4 i0 [3:0] $end
$var wire 4 5 i1 [3:0] $end
$var wire 4 6 i2 [3:0] $end
$var wire 4 7 i3 [3:0] $end
$var wire 4 8 i4 [3:0] $end
$var wire 4 9 i5 [3:0] $end
$var wire 4 : i6 [3:0] $end
$var wire 4 ; i7 [3:0] $end
$var wire 3 < s [2:0] $end
$var wire 4 = y [3:0] $end
$upscope $end
$upscope $end
$upscope $end
$enddefinitions $end
$comment Show the parameter values. $end
$dumpall
b11 $
b100 #
$end
#0
$dumpvars
b0 =
b0 <
b11 ;
b1 :
b0 9
b1111 8
b10 7
b11 6
b11 5
b0 4
b0 3
b11 2
b10 1
b1111 0
b0 /
b1 .
b11 -
b11 ,
b0 +
b10 *
b1 )
b0 (
b0 '
b10 &
b1 %
1"
b0 !
$end
#1
0"
b11 !
b11 3
b11 =
b10 +
b10 4
b1 -
b1 ;
b100 1
b100 7
b1 /
b1 9
b1 '
b1 (
b1 <
b11 &
b11 *
b101 2
b101 6
b1111 0
b1111 8
b10 %
b10 )
#2
0"
b100 !
b100 3
b100 =
b1 +
b1 4
b10 -
b10 ;
b10 1
b10 7
b0 /
b0 9
b10 '
b10 (
b10 <
b100 2
b100 6
b1110 0
b1110 8
b1 %
b1 )
#3
b100 !
b100 3
b100 =
b0 .
b0 :
b0 +
b0 4
b11 -
b11 ;
b100 1
b100 7
b1 /
b1 9
b11 '
b11 (
b11 <
b1 &
b1 *
b11 2
b11 6
b1 0
b1 8
b10 %
b10 )
#4
0"
b11 !
b11 3
b11 =
b101 ,
b101 5
b101 -
b101 ;
b1000 1
b1000 7
b10 /
b10 9
b100 '
b100 (
b100 <
b101 2
b101 6
b11 0
b11 8
b100 %
b100 )
#5
b10 !
b10 3
b10 =
b101 '
b101 (
b101 <
#6
1"
b0 !
b0 3
b0 =
b10 +
b10 4
b110 ,
b110 5
b100 -
b100 ;
b1100 1
b1100 7
b11 /
b11 9
b110 '
b110 (
b110 <
b10 &
b10 *
b1000 2
b1000 6
b100 0
b100 8
b110 %
b110 )
#7
0"
b1 !
b1 3
b1 =
b11 ,
b11 5
b1 -
b1 ;
b110 1
b110 7
b1 /
b1 9
b111 '
b111 (
b111 <
b101 2
b101 6
b1 0
b1 8
b11 %
b11 )
