lab4/mux_8_1_logic.v
module mux_8_1_logic (
    input [3:0] i0, i1, i2, i3, i4, i5, i6, i7, 
    input [2:0] s,                             
    output [3:0] y 
);                           

    assign y[3] = (i0[3] & ~s[0] & ~s[1] & ~s[2]) |
                  (i1[3] &  s[0] & ~s[1] & ~s[2]) |
                  (i2[3] & ~s[0] &  s[1] & ~s[2]) |
                  (i3[3] &  s[0] &  s[1] & ~s[2]) |
                  (i4[3] & ~s[0] & ~s[1] &  s[2]) |
                  (i5[3] &  s[0] & ~s[1] &  s[2]) |
                  (i6[3] & ~s[0] &  s[1] &  s[2]) |
                  (i7[3] &  s[0] &  s[1] &  s[2]);

    assign y[2] = (i0[2] & ~s[0] & ~s[1] & ~s[2]) |
                  (i1[2] &  s[0] & ~s[1] & ~s[2]) |
                  (i2[2] & ~s[0] &  s[1] & ~s[2]) |
                  (i3[2] &  s[0] &  s[1] & ~s[2]) |
                  (i4[2] & ~s[0] & ~s[1] &  s[2]) |
                  (i5[2] &  s[0] & ~s[1] &  s[2]) |
                  (i6[2] & ~s[0] &  s[1] &  s[2]) |
                  (i7[2] &  s[0] &  s[1] &  s[2]);

    assign y[1] = (i0[1] & ~s[0] & ~s[1] & ~s[2]) |
                  (i1[1] &  s[0] & ~s[1] & ~s[2]) |
                  (i2[1] & ~s[0] &  s[1] & ~s[2]) |
                  (i3[1] &  s[0] &  s[1] & ~s[2]) |
                  (i4[1] & ~s[0] & ~s[1] &  s[2]) |
                  (i5[1] &  s[0] & ~s[1] &  s[2]) |
                  (i6[1] & ~s[0] &  s[1] &  s[2]) |
                  (i7[1] &  s[0] &  s[1] &  s[2]);

    assign y[0] = (i0[0] & ~s[0] & ~s[1] & ~s[2]) |
                  (i1[0] &  s[0] & ~s[1] & ~s[2]) |
                  (i2[0] & ~s[0] &  s[1] & ~s[2]) |
                  (i3[0] &  s[0] &  s[1] & ~s[2]) |
                  (i4[0] & ~s[0] & ~s[1] &  s[2]) |
                  (i5[0] &  s[0] & ~s[1] &  s[2]) |
                  (i6[0] & ~s[0] &  s[1] &  s[2]) |
                  (i7[0] &  s[0] &  s[1] &  s[2]);

endmodule

lab4/mux_8_1_logic_tb.v
`include "mux_8_1_logic.v"

module mux_8_1_logic_tb;

    reg [3:0] i0, i1, i2, i3, i4, i5, i6, i7;
    reg [2:0] s;
    wire [3:0] y;

    mux_8_1_logic uut (
        .i0(i0),
        .i1(i1),
        .i2(i2),
        .i3(i3),
        .i4(i4),
        .i5(i5),
        .i6(i6),
        .i7(i7),
        .s(s),
        .y(y)
    );

    initial begin
        $dumpfile("mux_8_1_logic_tb.vcd");
        $dumpvars(0, mux_8_1_logic_tb);
    end

    initial begin
        i0 = 4'b0001;
        i1 = 4'b0010;
        i2 = 4'b0011;
        i3 = 4'b0100;
        i4 = 4'b0101;
        i5 = 4'b0110;
        i6 = 4'b0111;
        i7 = 4'b1000;

        s = 3'b000; #1;
        s = 3'b001; #1;
        s = 3'b010; #1;
        s = 3'b011; #1;
        s = 3'b100; #1;
        s = 3'b101; #1;
        s = 3'b110; #1;
        s = 3'b111; #1;

    end

endmodule

lab4/mux_8_1_logic_tb.vcd
$date
	Thu Nov  7 06:17:19 2024
$end
$version
	Icarus Verilog
$end
$timescale
	1s
$end
$scope module mux_8_1_logic_tb $end
$var wire 4 ! y [3:0] $end
$var reg 4 " i0 [3:0] $end
$var reg 4 # i1 [3:0] $end
$var reg 4 $ i2 [3:0] $end
$var reg 4 % i3 [3:0] $end
$var reg 4 & i4 [3:0] $end
$var reg 4 ' i5 [3:0] $end
$var reg 4 ( i6 [3:0] $end
$var reg 4 ) i7 [3:0] $end
$var reg 3 * s [2:0] $end
$scope module uut $end
$var wire 4 + i0 [3:0] $end
$var wire 4 , i1 [3:0] $end
$var wire 4 - i2 [3:0] $end
$var wire 4 . i3 [3:0] $end
$var wire 4 / i4 [3:0] $end
$var wire 4 0 i5 [3:0] $end
$var wire 4 1 i6 [3:0] $end
$var wire 4 2 i7 [3:0] $end
$var wire 3 3 s [2:0] $end
$var wire 4 4 y [3:0] $end
$upscope $end
$upscope $end
$enddefinitions $end
$comment Show the parameter values. $end
$dumpall
$end
#0
$dumpvars
b1 4
b0 3
b1000 2
b111 1
b110 0
b101 /
b100 .
b11 -
b10 ,
b1 +
b0 *
b1000 )
b111 (
b110 '
b101 &
b100 %
b11 $
b10 #
b1 "
b1 !
$end
#1
b10 !
b10 4
b1 *
b1 3
#2
b11 !
b11 4
b10 *
b10 3
#3
b100 !
b100 4
b11 *
b11 3
#4
b101 !
b101 4
b100 *
b100 3
#5
b110 !
b110 4
b101 *
b101 3
#6
b111 !
b111 4
b110 *
b110 3
#7
b1000 !
b1000 4
b111 *
b111 3
