lab2/full_adder.v
module AND (
    input a,
    input b,
    output y
);
    assign y = a & b;
endmodule 

module OR (
    input a,
    input b, 
    output y
);
    assign y = a | b;
endmodule

module XOR (
    input a,
    input b,
    output y
);
    assign y = a ^ b;
endmodule

module Full_Adder (
    input A,
    input B,
    input Cin,
    output S,
    output Cout
);
    wire w1, w2, w3;

    XOR U1 (.a(A), .b(B), .y(w1)); 
    XOR U2 (.a(w1), .b(Cin), .y(S));

    AND U3 (.a(A), .b(B), .y(w2));  
    AND U4 (.a(w1), .b(Cin), .y(w3)); 

    OR U5 (.a(w2), .b(w3), .y(Cout));  
endmodule

lab2/full_adder_tb.v
// tb for full adder

`include "full_adder.v"

module full_adder_tb;

    reg A, B, CIN;   // UUT inputs
    wire S, COUT;    // UUT outputs

    // Full adder instance
    Full_Adder uut (.A(A), .B(B), .Cin(CIN), .S(S), .Cout(COUT));

    initial begin
        $dumpfile("full_adder_tb.vcd");
        $dumpvars(0, full_adder_tb);
    end

    initial begin
        A = 1'b0; B = 1'b0; CIN = 1'b0; #1;
        A = 1'b0; B = 1'b0; CIN = 1'b1; #1;
        A = 1'b0; B = 1'b1; CIN = 1'b0; #1;
        A = 1'b0; B = 1'b1; CIN = 1'b1; #1;
        A = 1'b1; B = 1'b0; CIN = 1'b0; #1;
        A = 1'b1; B = 1'b0; CIN = 1'b1; #1;
        A = 1'b1; B = 1'b1; CIN = 1'b0; #1;
        A = 1'b1; B = 1'b1; CIN = 1'b1; #1;
    end
  
endmodule

lab2/full_adder_tb.vcd
$date
	Thu Nov  7 05:44:27 2024
$end
$version
	Icarus Verilog
$end
$timescale
	1s
$end
$scope module full_adder_tb $end
$var wire 1 ! S $end
$var wire 1 " COUT $end
$var reg 1 # A $end
$var reg 1 $ B $end
$var reg 1 % CIN $end
$scope module uut $end
$var wire 1 # A $end
$var wire 1 $ B $end
$var wire 1 % Cin $end
$var wire 1 & w3 $end
$var wire 1 ' w2 $end
$var wire 1 ( w1 $end
$var wire 1 ! S $end
$var wire 1 " Cout $end
$scope module U1 $end
$var wire 1 # a $end
$var wire 1 $ b $end
$var wire 1 ( y $end
$upscope $end
$scope module U2 $end
$var wire 1 ( a $end
$var wire 1 % b $end
$var wire 1 ! y $end
$upscope $end
$scope module U3 $end
$var wire 1 # a $end
$var wire 1 $ b $end
$var wire 1 ' y $end
$upscope $end
$scope module U4 $end
$var wire 1 ( a $end
$var wire 1 % b $end
$var wire 1 & y $end
$upscope $end
$scope module U5 $end
$var wire 1 ' a $end
$var wire 1 & b $end
$var wire 1 " y $end
$upscope $end
$upscope $end
$upscope $end
$enddefinitions $end
$comment Show the parameter values. $end
$dumpall
$end
#0
$dumpvars
0(
0'
0&
0%
0$
0#
0"
0!
$end
#1
1!
1%
#2
1(
0%
1$
#3
1"
0!
1&
1%
#4
0"
1!
0&
0%
0$
1#
#5
1"
0!
1&
1%
#6
0&
0(
1'
0%
1$
#7
1!
1%
