lab3/bcd_7seg.v
module bcd_7seg (
    // Inputs
    input [3:0] bcd,

    // Outputs
    output reg [6:0] seg
);

    always @(*) begin
        case(bcd)
            4'b0000: seg = 7'b0000001;
            4'b0001: seg = 7'b1001111;
            4'b0010: seg = 7'b0010010;
            4'b0011: seg = 7'b0000110;
            4'b0100: seg = 7'b1001100;
            4'b0101: seg = 7'b0100100;
            4'b0110: seg = 7'b0100000;
            4'b0111: seg = 7'b0001111;
            4'b1000: seg = 7'b0000000;
            4'b1001: seg = 7'b0000100;
            4'b1010: seg = 7'b0001000;
            4'b1011: seg = 7'b1100000;
            4'b1100: seg = 7'b0110001;
            4'b1101: seg = 7'b1000010;
            4'b1110: seg = 7'b0110000;
            4'b1111: seg = 7'b0111000;
            default: seg = 7'b1111111;
        endcase
    end

endmodule

lab3/bcd_7seg_tb.v
`include "bcd_7seg.v"

module bcd_7seg_tb;

    reg [3:0] bcd;
    wire [6:0] seg;

    bcd_7seg uut (
        .bcd(bcd),
        .seg(seg)
    );

    initial begin
        $dumpfile("bcd_7seg_tb.vcd");
        $dumpvars(0, bcd_7seg_tb);

        bcd = 4'b0000; #1;
        bcd = 4'b0001; #1;
        bcd = 4'b0010; #1;
        bcd = 4'b0011; #1;
        bcd = 4'b0100; #1;
        bcd = 4'b0101; #1;
        bcd = 4'b0110; #1;
        bcd = 4'b0111; #1;
        bcd = 4'b1000; #1;
        bcd = 4'b1001; #1;
        bcd = 4'b1010; #1;
        bcd = 4'b1011; #1;
        bcd = 4'b1100; #1;
        bcd = 4'b1101; #1;
        bcd = 4'b1110; #1;
        bcd = 4'b1111; #1;
    end

endmodule

lab3/bcd_7seg_tb.vcd
$date
	Thu Nov  7 05:51:21 2024
$end
$version
	Icarus Verilog
$end
$timescale
	1s
$end
$scope module bcd_7seg_tb $end
$var wire 7 ! seg [6:0] $end
$var reg 4 " bcd [3:0] $end
$scope module uut $end
$var wire 4 # bcd [3:0] $end
$var reg 7 $ seg [6:0] $end
$upscope $end
$upscope $end
$enddefinitions $end
$comment Show the parameter values. $end
$dumpall
$end
#0
$dumpvars
b1 $
b0 #
b0 "
b1 !
$end
#1
b1001111 !
b1001111 $
b1 "
b1 #
#2
b10010 !
b10010 $
b10 "
b10 #
#3
b110 !
b110 $
b11 "
b11 #
#4
b1001100 !
b1001100 $
b100 "
b100 #
#5
b100100 !
b100100 $
b101 "
b101 #
#6
b100000 !
b100000 $
b110 "
b110 #
#7
b1111 !
b1111 $
b111 "
b111 #
#8
b0 !
b0 $
b1000 "
b1000 #
#9
b100 !
b100 $
b1001 "
b1001 #
#10
b1000 !
b1000 $
b1010 "
b1010 #
#11
b1100000 !
b1100000 $
b1011 "
b1011 #
#12
b110001 !
b110001 $
b1100 "
b1100 #
#13
b1000010 !
b1000010 $
b1101 "
b1101 #
#14
b110000 !
b110000 $
b1110 "
b1110 #
#15
b111000 !
b111000 $
b1111 "
b1111 #
